bldr/VERSION
bldr/__init__.py
bldr/bldr.py
bldr/cli.py
bldr/config.py
bldr/docker_utils.py
bldr/utils.py
bldr/version.py
bldr/data/Dockerfile.tpl
bldr/data/files/etc/apt/apt.conf.d/91-debconf
bldr/data/files/etc/apt/apt.conf.d/99-debug
bldr/data/files/etc/apt/preferences.d/pin_local
bldr/data/files/etc/apt/sources.list.d/local-apt.list
bldr/data/files/etc/sudoers.d/keep_env
bldr/data/files/usr/local/bin/build-deb
bldr/data/files/usr/local/bin/init-docker-image
bldr/data/files/usr/local/bin/install-build-deps
bldr/data/files/usr/local/bin/noninteractive-apt-get
bldr/data/files/usr/local/bin/prepare-quilt-package
bldr/data/files/usr/local/bin/reindex
bldr/data/hooks/post-install-deps
bldr/data/hooks/pre-build
bldr/data/hooks/pre-init
bldr/data/hooks/pre-install-deps
bldr-0.0.21.dist-info/licenses/LICENSE
bldr-0.0.21.dist-info/METADATA
bldr-0.0.21.dist-info/WHEEL
bldr-0.0.21.dist-info/entry_points.txt
bldr-0.0.21.dist-info/top_level.txt
bldr-0.0.21.dist-info/RECORD
