Metadata-Version: 2.4
Name: bldr
Version: 0.0.21
Summary: Build debian packages in a clean docker environment
Home-page: https://www.github.com/OneIdentity/bldr
Author: BLDR Developers
Author-email: noreply@oneidentity.com
License: MIT
Classifier: Development Status :: 4 - Beta
Classifier: Intended Audience :: System Administrators
Classifier: License :: OSI Approved :: MIT License
Classifier: Operating System :: POSIX :: Linux
Classifier: Programming Language :: Python
Classifier: Programming Language :: Python :: 3
Classifier: Programming Language :: Python :: 3.10
Classifier: Programming Language :: Python :: 3.11
Classifier: Programming Language :: Python :: 3.12
Classifier: Topic :: System :: Systems Administration
Classifier: Topic :: Utilities
Requires-Python: >=3.10
License-File: LICENSE
Requires-Dist: certifi==2026.1.4
Requires-Dist: charset-normalizer==3.4.4
Requires-Dist: docker==7.1.0
Requires-Dist: dockerpty==0.4.1
Requires-Dist: idna==3.11
Requires-Dist: importlib-resources==6.5.2
Requires-Dist: requests==2.32.5
Requires-Dist: six==1.17.0
Requires-Dist: urllib3==2.6.3
Provides-Extra: dev
Requires-Dist: autopep8==2.3.2; extra == "dev"
Requires-Dist: coverage[toml]==7.13.1; extra == "dev"
Requires-Dist: exceptiongroup==1.3.1; extra == "dev"
Requires-Dist: flake8==7.3.0; extra == "dev"
Requires-Dist: iniconfig==2.3.0; extra == "dev"
Requires-Dist: librt==0.7.8; extra == "dev"
Requires-Dist: mccabe==0.7.0; extra == "dev"
Requires-Dist: mypy==1.19.1; extra == "dev"
Requires-Dist: mypy-extensions==1.1.0; extra == "dev"
Requires-Dist: packaging==25.0; extra == "dev"
Requires-Dist: pathspec==1.0.3; extra == "dev"
Requires-Dist: pluggy==1.6.0; extra == "dev"
Requires-Dist: pycodestyle==2.14.0; extra == "dev"
Requires-Dist: pyflakes==3.4.0; extra == "dev"
Requires-Dist: pygments==2.19.2; extra == "dev"
Requires-Dist: pytest==9.0.2; extra == "dev"
Requires-Dist: pytest-console-scripts==1.4.1; extra == "dev"
Requires-Dist: pytest-cov==7.0.0; extra == "dev"
Requires-Dist: tomli==2.4.0; extra == "dev"
Requires-Dist: types-requests==2.32.4.20260107; extra == "dev"
Requires-Dist: types-setuptools==80.9.0.20251223; extra == "dev"
Requires-Dist: typing-extensions==4.15.0; extra == "dev"
Requires-Dist: urllib3==2.6.3; extra == "dev"
Dynamic: author
Dynamic: author-email
Dynamic: classifier
Dynamic: description
Dynamic: description-content-type
Dynamic: home-page
Dynamic: license
Dynamic: license-file
Dynamic: provides-extra
Dynamic: requires-dist
Dynamic: requires-python
Dynamic: summary
